bio_attention/__init__.py
bio_attention/attention.py
bio_attention/embed.py
bio_attention/positional.py
bio_attention-0.1.15.dist-info/licenses/LICENSE
bio_attention-0.1.15.dist-info/METADATA
bio_attention-0.1.15.dist-info/WHEEL
bio_attention-0.1.15.dist-info/top_level.txt
bio_attention-0.1.15.dist-info/RECORD
