Metadata-Version: 2.4
Name: bio-attention
Version: 0.1.15
Summary: Simple implementations of attention modules adapted for the biological data domain
Home-page: https://github.com/gdewael/bio-attention
Author: Gaetan De Waele
Requires-Python: >=3.8
License-File: LICENSE
Requires-Dist: torch>2.3.0
Requires-Dist: einops
Dynamic: license-file
